{"leader":"00000ces a2200721 a 4500","fields":[{"001":"000460553"},{"005":"20131010194026.0"},{"006":"s x        f0    0"},{"007":"ad|canza"},{"008":"750210c19539999dcu       e  f  0   eng d"},{"010":{"ind1":" ","ind2":" ","subfields":[{"a":"sf 85008009"},{"z":"sn 82000185"}]}},{"022":{"ind1":"0","ind2":" ","subfields":[{"a":"0375-7978"},{"z":"0146-7859"}]}},{"030":{"ind1":" ","ind2":" ","subfields":[{"a":"XGHAAQ"}]}},{"035":{"ind1":" ","ind2":" ","subfields":[{"a":"(MnU)notisANH8061"}]}},{"035":{"ind1":" ","ind2":" ","subfields":[{"a":"(OCoLC)1166303"}]}},{"035":{"ind1":" ","ind2":" ","subfields":[{"a":"(MCDIA)000460553"}]}},{"040":{"ind1":" ","ind2":" ","subfields":[{"a":"DI"},{"c":"DI"},{"d":"NSDP"},{"d":"OCoLC"},{"d":"MH"},{"d":"DLC"},{"d":"AIP001701557"},{"d":"DLC"},{"d":"MCM"},{"d":"NST"},{"d":"DNAL"},{"d":"NST"},{"d":"OCoLC"},{"d":"MnU"}]}},{"042":{"ind1":" ","ind2":" ","subfields":[{"a":"nsdp"},{"a":"lcd"}]}},{"043":{"ind1":" ","ind2":" ","subfields":[{"a":"n-us---"}]}},{"050":{"ind1":"0","ind2":"4","subfields":[{"a":"G1200.C3 svar"},{"b":".G4x"}]}},{"050":{"ind1":"0","ind2":"0","subfields":[{"a":"G3701s"},{"b":".C3 var. .U5"}]}},{"070":{"ind1":"0","ind2":" ","subfields":[{"a":"G3701s.C3"},{"b":"var. U5"}]}},{"072":{"ind1":" ","ind2":"0","subfields":[{"a":"P200"}]}},{"072":{"ind1":" ","ind2":"7","subfields":[{"a":"C3"},{"2":"lcg"}]}},{"110":{"ind1":"2","ind2":" ","subfields":[{"a":"Geological Survey (U.S.)."}]}},{"210":{"ind1":"0","ind2":" ","subfields":[{"a":"Hydrol. invest. atlas"}]}},{"222":{"ind1":" ","ind2":"0","subfields":[{"a":"Hydrologic investigations atlas"}]}},{"245":{"ind1":"1","ind2":"0","subfields":[{"a":"Hydrologic investigations atlas /"},{"c":"Department of the Interior, United States Geological Survey."}]}},{"255":{"ind1":" ","ind2":" ","subfields":[{"a":"Scales vary."}]}},{"260":{"ind1":" ","ind2":" ","subfields":[{"a":"Washington, D.C. :"},{"b":"U.S. Geological Survey :"},{"b":"For sale by the U.S. Geological Survey,"},{"c":"1954-"}]}},{"300":{"ind1":" ","ind2":" ","subfields":[{"a":"v. :"},{"b":"ill., maps (some col.) ;"},{"c":"107 x 145 cm. or smaller, some folded, in envelopes 30 x 24 cm."}]}},{"310":{"ind1":" ","ind2":" ","subfields":[{"a":"Irregular"}]}},{"362":{"ind1":"0","ind2":" ","subfields":[{"a":"HA 1-"}]}},{"500":{"ind1":" ","ind2":" ","subfields":[{"a":"Predominant scale: 1:24,000; large regions at scale: 1:250,000."}]}},{"515":{"ind1":" ","ind2":" ","subfields":[{"a":"Atlas HA 2 issued in 1953."}]}},{"510":{"ind1":"2","ind2":" ","subfields":[{"a":"GeoRef"},{"x":"0197-7482"}]}},{"550":{"ind1":" ","ind2":" ","subfields":[{"a":"Individual issues prepared in cooperation with various local agencies."}]}},{"650":{"ind1":" ","ind2":"0","subfields":[{"a":"Hydrology"},{"z":"United States"},{"v":"Maps."}]}},{"650":{"ind1":" ","ind2":"0","subfields":[{"a":"Hydrology"},{"z":"United States"},{"v":"Atlases."}]}},{"650":{"ind1":" ","ind2":"0","subfields":[{"a":"Hydrology"},{"x":"Research"},{"v":"Maps."}]}},{"650":{"ind1":" ","ind2":"0","subfields":[{"a":"Hydrology"},{"x":"Research"},{"v":"Atlases."}]}},{"655":{"ind1":" ","ind2":"7","subfields":[{"a":"Maps."},{"2":"lcgft"}]}},{"955":{"ind1":" ","ind2":" ","subfields":[{"b":"31951p001592186"},{"v":"HA-730-G (1995)"}]}}]}
