{ "leader" : "01312nam a2200277Ia 4500", "fields" : [ { "001" : "021641009" }, { "005" : "20120623035800.0" }, { "008" : "810515s1981    dcuab    b   f001|0 eng d" }, { "035" : { "ind1" : " ", "ind2" : " ", "subfields" : [ { "a" : "(OCoLC)07421293" } ] } }, { "040" : { "ind1" : " ", "ind2" : " ", "subfields" : [ { "a" : "AGL" }, { "c" : "AGL" }, { "d" : "FHM" } ] } }, { "072" : { "ind1" : " ", "ind2" : " ", "subfields" : [ { "a" : "F830" }, { "a" : "K001" } ] } }, { "074" : { "ind1" : " ", "ind2" : " ", "subfields" : [ { "a" : "16" } ] } }, { "086" : { "ind1" : "0", "ind2" : " ", "subfields" : [ { "a" : "A 1.36:1631" } ] } }, { "099" : { "ind1" : " ", "ind2" : " ", "subfields" : [ { "a" : "A 1.36:" }, { "a" : "1631" } ] } }, { "245" : { "ind1" : "0", "ind2" : "4", "subfields" : [ { "a" : "The Southern pine beetle /" }, { "c" : "edited by Robert C. Thatcher ... [et al.]." } ] } }, { "260" : { "ind1" : " ", "ind2" : " ", "subfields" : [ { "a" : "[Washington, D.C.] :" }, { "b" : "U.S.D.A., Forest Service, Science and Education Administration," }, { "c" : "[1981]" } ] } }, { "300" : { "ind1" : " ", "ind2" : " ", "subfields" : [ { "a" : "xiii, 267 p. :" }, { "b" : "ill., maps ;" }, { "c" : "29 cm." } ] } }, { "490" : { "ind1" : "0", "ind2" : " ", "subfields" : [ { "a" : "United States. Dept. of Agriculture. Technical bulletin ; 1631" }, { "5" : "FTS" } ] } }, { "490" : { "ind1" : "1", "ind2" : " ", "subfields" : [ { "a" : "Technical bulletin ;" }, { "v" : "1631" }, { "5" : "FMFIU" } ] } }, { "504" : { "ind1" : " ", "ind2" : " ", "subfields" : [ { "a" : "Includes bibliographies and index." } ] } }, { "650" : { "ind1" : " ", "ind2" : "0", "subfields" : [ { "a" : "Southern pine beetle" } ] } }, { "700" : { "ind1" : "1", "ind2" : " ", "subfields" : [ { "a" : "Thatcher, Robert C." } ] } }, { "710" : { "ind1" : "2", "ind2" : " ", "subfields" : [ { "a" : "Expanded Southern Pine Beetle Research & Applications Program (U.S.)" } ] } }, { "830" : { "ind1" : " ", "ind2" : "0", "subfields" : [ { "a" : "Technical bulletin (United States. Dept. of Agriculture) ;" }, { "v" : "1631." } ] } }, { "955" : { "ind1" : " ", "ind2" : " ", "subfields" : [ { "b" : "32102800368934" }, { "v" : "A 1. 36:1631" } ] } } ], "file_name" : "/htdata/govdocs/MARC/raw_xml/flasus-20140131-0300-92.xml" }
